<delegation_and_integration>
  <overview>
    This document defines how the project online API Client Code mode integrates with
    other modes and maintains specification-fidelity during collaboration.
  </overview>

  <delegation_from_code_mode>
    project online Code mode automatically delegates API client tasks to prevent
    hallucinations and ensure specification compliance.

    Delegation triggers (when to invoke) defined in:
    ../../sdlc/shared/api-client-role-definition.md
  </delegation_from_code_mode>

  <scope_boundaries>
    Scope boundaries defined in: ../../sdlc/shared/api-client-role-definition.md
  </scope_boundaries>

  <conflict_resolution>
    Conflict resolution templates defined in:
    ../../sdlc/shared/api-client-code-generation.md
  </conflict_resolution>

  <quality_assurance>
    Pre and post implementation validation requirements defined in:
    ../../sdlc/shared/api-client-code-generation.md
  </quality_assurance>

  <completion_reporting>
    Completion report template and issue escalation defined in:
    ../../sdlc/shared/api-client-code-generation.md
  </completion_reporting>
</delegation_and_integration>